LICENSE
xkcd_cli/__init__.py
xkcd_cli/iv.py
xkcd_cli/iv_test.py
xkcd_cli/xkcd.py
dcs_xkcd_cli-2.0.0.dist-info/entry_points.txt
dcs_xkcd_cli-2.0.0.dist-info/LICENSE
dcs_xkcd_cli-2.0.0.dist-info/WHEEL
dcs_xkcd_cli-2.0.0.dist-info/METADATA
dcs_xkcd_cli-2.0.0.dist-info/RECORD
