Metadata-Version: 2.1
Name: dcs-xkcd-cli
Version: 2.0.0
Summary: Get your daily dose of xkcd directly from the terminal! 🤩
Home-page: https://github.com/dotcs/xkcd-cli
License: MIT
Keywords: cli,cli-app,xkcd,xkcd-comics
Author: dotcs
Author-email: repositories@dotcs.me
Requires-Python: >=3.8,<4.0
Classifier: License :: OSI Approved :: MIT License
Classifier: Programming Language :: Python :: 3
Classifier: Programming Language :: Python :: 3.10
Classifier: Programming Language :: Python :: 3.8
Classifier: Programming Language :: Python :: 3.9
Requires-Dist: Pillow (>=9.1.1,<10.0.0)
Requires-Dist: beautifulsoup4 (>=4.11,<5.0)
Requires-Dist: requests (>=2.27,<3.0)
Requires-Dist: typer (>=0.4,<0.5)
Project-URL: Repository, https://github.com/dotcs/xkcd-cli
